{
  "last_node_id": 4,
  "last_link_id": 3,
  "nodes": [
    {
      "id": 1,
      "type": "KlingDirect_Auth",
      "pos": [
        60,
        60
      ],
      "size": [
        320,
        148
      ],
      "flags": {},
      "order": 1,
      "mode": 0,
      "inputs": [],
      "outputs": [
        {
          "name": "auth",
          "type": "KLING_AUTH",
          "links": [
            1
          ],
          "slot_index": 0
        }
      ],
      "properties": {
        "recipe_id": "auth",
        "Node name for S&R": "KlingDirect_Auth"
      },
      "widgets_values": [
        "",
        "",
        false
      ]
    },
    {
      "id": 2,
      "type": "LoadImage",
      "pos": [
        60,
        258
      ],
      "size": [
        320,
        122
      ],
      "flags": {},
      "order": 2,
      "mode": 0,
      "inputs": [],
      "outputs": [
        {
          "name": "IMAGE",
          "type": "IMAGE",
          "links": [
            2
          ],
          "slot_index": 0
        },
        {
          "name": "MASK",
          "type": "MASK",
          "links": [],
          "slot_index": 1
        }
      ],
      "properties": {
        "recipe_id": "img",
        "Node name for S&R": "LoadImage"
      },
      "widgets_values": [
        ""
      ]
    },
    {
      "id": 3,
      "type": "KlingDirect_ImageOmni",
      "pos": [
        460,
        60
      ],
      "size": [
        320,
        242
      ],
      "flags": {},
      "order": 3,
      "mode": 0,
      "inputs": [
        {
          "name": "auth",
          "type": "KLING_AUTH",
          "link": 1
        },
        {
          "name": "image_1",
          "type": "IMAGE",
          "link": 2
        }
      ],
      "outputs": [
        {
          "name": "image",
          "type": "IMAGE",
          "links": [
            3
          ],
          "slot_index": 0
        },
        {
          "name": "url",
          "type": "STRING",
          "links": [],
          "slot_index": 1
        },
        {
          "name": "task_id",
          "type": "STRING",
          "links": [],
          "slot_index": 2
        }
      ],
      "properties": {
        "recipe_id": "omni",
        "Node name for S&R": "KlingDirect_ImageOmni"
      },
      "widgets_values": [
        "Reimagine this in cyberpunk style: neon lights, rain-slicked streets, holographic signs",
        "16:9",
        "1k"
      ]
    },
    {
      "id": 4,
      "type": "PreviewImage",
      "pos": [
        860,
        60
      ],
      "size": [
        320,
        82
      ],
      "flags": {},
      "order": 4,
      "mode": 0,
      "inputs": [
        {
          "name": "images",
          "type": "IMAGE",
          "link": 3
        }
      ],
      "outputs": [],
      "properties": {
        "recipe_id": "preview",
        "Node name for S&R": "PreviewImage"
      },
      "widgets_values": []
    }
  ],
  "links": [
    [
      1,
      1,
      0,
      3,
      0,
      "KLING_AUTH"
    ],
    [
      2,
      2,
      0,
      3,
      1,
      "IMAGE"
    ],
    [
      3,
      3,
      0,
      4,
      0,
      "IMAGE"
    ]
  ],
  "groups": [
    {
      "title": "Setup",
      "bounding": [
        35,
        -1,
        370,
        406
      ],
      "color": "#3F789E",
      "font_size": 24,
      "locked": false
    },
    {
      "title": "Action",
      "bounding": [
        435,
        -1,
        370,
        328
      ],
      "color": "#3F789E",
      "font_size": 24,
      "locked": false
    },
    {
      "title": "Output",
      "bounding": [
        835,
        -1,
        370,
        168
      ],
      "color": "#3F789E",
      "font_size": 24,
      "locked": false
    }
  ],
  "config": {},
  "extra": {
    "ds": {
      "scale": 1.0,
      "offset": [
        0,
        0
      ]
    },
    "description": "Reimagine an existing image with a text prompt using Kling's omni image model \u2014 style transfer, scene changes, and creative edits.",
    "title": "Kling \u2014 Image Omni",
    "tier": 1,
    "pack": "ComfyUI-Kling-Direct"
  },
  "version": 0.4
}